scrobble/__init__.py
scrobble/app.py
scrobble/barcode_scanner.py
scrobble/lastfm.py
scrobble/musicbrainz.py
scrobble/pushover.py
scrobble/utils.py
scrobble-0.2.1.dist-info/LICENSE.txt
scrobble-0.2.1.dist-info/METADATA
scrobble-0.2.1.dist-info/WHEEL
scrobble-0.2.1.dist-info/entry_points.txt
scrobble-0.2.1.dist-info/top_level.txt
scrobble-0.2.1.dist-info/RECORD
