Metadata-Version: 2.1
Name: scrobble
Version: 0.2.1
Summary: Scrobble CDs to your last.fm account.
Author-email: Sherif Soliman <hi@sherif.io>
Project-URL: Homepage, https://github.com/sheriferson/scrobble
Keywords: last.fm,scrobble,cd,music
Classifier: Topic :: Utilities
Classifier: Programming Language :: Python :: 3
Requires-Python: >=3.11
License-File: LICENSE.txt
Requires-Dist: musicbrainzngs
Requires-Dist: parsedatetime
Requires-Dist: python-dateutil
Requires-Dist: pylast
Requires-Dist: rich
Requires-Dist: typer[all]
Requires-Dist: opencv-python
Provides-Extra: test
Requires-Dist: scrobble ; extra == 'test'
Requires-Dist: pytest ; extra == 'test'
Requires-Dist: pytest-cov ; extra == 'test'
